LICENSE
README.md
setup.py
example/__init__.py
example/demo_report.py
example/demo_vaas.py
src/__init__.py
src/vaas/__init__.py
src/vaas/config.py
src/vaas/credentials.py
src/vaas/report.py
src/vaas/tools.py
src/vaas/vaas.py
vaas_sdk_python.egg-info/PKG-INFO
vaas_sdk_python.egg-info/SOURCES.txt
vaas_sdk_python.egg-info/dependency_links.txt
vaas_sdk_python.egg-info/top_level.txt