Metadata-Version: 1.0
Name: vaas-sdk-python
Version: 1.0.1
Summary: vaas-sdk
Home-page: https://github.com/yilanyun/vaas-sdk-python.git
Author: wangmq
Author-email: UNKNOWN
License: UNKNOWN
Platform: UNKNOWN
